mega/__init__.py
mega/crypto.py
mega/errors.py
mega/mega.py
mega.py-1.0.8.dist-info/LICENSE
mega.py-1.0.8.dist-info/METADATA
mega.py-1.0.8.dist-info/WHEEL
mega.py-1.0.8.dist-info/top_level.txt
mega.py-1.0.8.dist-info/RECORD
