Metadata-Version: 2.1
Name: mega.py
Version: 1.0.8
Summary: Python lib for the Mega.co.nz API
Home-page: https://github.com/odwyersoftware/mega.py
Author: O'Dwyer Software
Author-email: hello@odwyer.software
License: Creative Commons Attribution-Noncommercial-Share Alike license
Platform: UNKNOWN
Classifier: Intended Audience :: Developers
Classifier: Operating System :: OS Independent
Classifier: Programming Language :: Python
Classifier: Programming Language :: Python :: 3
Classifier: Topic :: Internet :: WWW/HTTP
